{
	"textures": [
		{
			"image": "undead_top_walk.png",
			"format": "RGBA8888",
			"size": {
				"w": 304,
				"h": 51
			},
			"scale": 1,
			"frames": [
				{
					"filename": "undead_walk-0.png",
					"rotated": false,
					"trimmed": true,
					"sourceSize": {
						"w": 64,
						"h": 64
					},
					"spriteSourceSize": {
						"x": 16,
						"y": 14,
						"w": 32,
						"h": 48
					},
					"frame": {
						"x": 1,
						"y": 1,
						"w": 32,
						"h": 48
					},
					"anchor": {
						"x": 0.5,
						"y": 0.5
					}
				},
				{
					"filename": "undead_walk-1.png",
					"rotated": false,
					"trimmed": true,
					"sourceSize": {
						"w": 64,
						"h": 64
					},
					"spriteSourceSize": {
						"x": 16,
						"y": 14,
						"w": 32,
						"h": 48
					},
					"frame": {
						"x": 35,
						"y": 1,
						"w": 32,
						"h": 48
					},
					"anchor": {
						"x": 0.5,
						"y": 0.5
					}
				},
				{
					"filename": "undead_walk-2.png",
					"rotated": false,
					"trimmed": true,
					"sourceSize": {
						"w": 64,
						"h": 64
					},
					"spriteSourceSize": {
						"x": 16,
						"y": 14,
						"w": 32,
						"h": 49
					},
					"frame": {
						"x": 69,
						"y": 1,
						"w": 32,
						"h": 49
					},
					"anchor": {
						"x": 0.5,
						"y": 0.5
					}
				},
				{
					"filename": "undead_walk-3.png",
					"rotated": false,
					"trimmed": true,
					"sourceSize": {
						"w": 64,
						"h": 64
					},
					"spriteSourceSize": {
						"x": 16,
						"y": 15,
						"w": 31,
						"h": 49
					},
					"frame": {
						"x": 103,
						"y": 1,
						"w": 31,
						"h": 49
					},
					"anchor": {
						"x": 0.5,
						"y": 0.5
					}
				},
				{
					"filename": "undead_walk-4.png",
					"rotated": false,
					"trimmed": true,
					"sourceSize": {
						"w": 64,
						"h": 64
					},
					"spriteSourceSize": {
						"x": 16,
						"y": 14,
						"w": 32,
						"h": 49
					},
					"frame": {
						"x": 136,
						"y": 1,
						"w": 32,
						"h": 49
					},
					"anchor": {
						"x": 0.5,
						"y": 0.5
					}
				},
				{
					"filename": "undead_walk-5.png",
					"rotated": false,
					"trimmed": true,
					"sourceSize": {
						"w": 64,
						"h": 64
					},
					"spriteSourceSize": {
						"x": 16,
						"y": 14,
						"w": 32,
						"h": 48
					},
					"frame": {
						"x": 170,
						"y": 1,
						"w": 32,
						"h": 48
					},
					"anchor": {
						"x": 0.5,
						"y": 0.5
					}
				},
				{
					"filename": "undead_walk-6.png",
					"rotated": false,
					"trimmed": true,
					"sourceSize": {
						"w": 64,
						"h": 64
					},
					"spriteSourceSize": {
						"x": 16,
						"y": 14,
						"w": 32,
						"h": 49
					},
					"frame": {
						"x": 204,
						"y": 1,
						"w": 32,
						"h": 49
					},
					"anchor": {
						"x": 0.5,
						"y": 0.5
					}
				},
				{
					"filename": "undead_walk-7.png",
					"rotated": false,
					"trimmed": true,
					"sourceSize": {
						"w": 64,
						"h": 64
					},
					"spriteSourceSize": {
						"x": 17,
						"y": 15,
						"w": 31,
						"h": 49
					},
					"frame": {
						"x": 238,
						"y": 1,
						"w": 31,
						"h": 49
					},
					"anchor": {
						"x": 0.5,
						"y": 0.5
					}
				},
				{
					"filename": "undead_walk-8.png",
					"rotated": false,
					"trimmed": true,
					"sourceSize": {
						"w": 64,
						"h": 64
					},
					"spriteSourceSize": {
						"x": 16,
						"y": 14,
						"w": 32,
						"h": 49
					},
					"frame": {
						"x": 271,
						"y": 1,
						"w": 32,
						"h": 49
					},
					"anchor": {
						"x": 0.5,
						"y": 0.5
					}
				}
			]
		}
	],
	"meta": {
		"app": "https://www.codeandweb.com/texturepacker",
		"version": "3.0",
		"smartupdate": "$TexturePacker:SmartUpdate:3fdba292479698a134160f344830b707:a70b1431980dd7b4248a795c93a9ffdf:044df5c689fd147ce4ed1d706a158951$"
	}
}
